ShapeChecker/ShapeCheck.py
ShapeChecker/__init__.py
ShapeChecker-0.2.0.dist-info/METADATA
ShapeChecker-0.2.0.dist-info/WHEEL
ShapeChecker-0.2.0.dist-info/top_level.txt
ShapeChecker-0.2.0.dist-info/RECORD
