Metadata-Version: 2.1
Name: ShapeChecker
Version: 0.2.0
Summary: ShapeChecker assist you when doing tensors manipulation
Home-page: https://github.com/Etienne-Meunier/ShapeChecker
Author: Etienne Meunier
Author-email: etiennemeunier@live.fr
License: BSD 2-clause
Platform: UNKNOWN
Classifier: Development Status :: 1 - Planning
Classifier: Intended Audience :: Science/Research
Classifier: License :: OSI Approved :: BSD License
Classifier: Operating System :: POSIX :: Linux
Classifier: Programming Language :: Python :: 2
Classifier: Programming Language :: Python :: 2.7
Classifier: Programming Language :: Python :: 3
Classifier: Programming Language :: Python :: 3.4
Classifier: Programming Language :: Python :: 3.5
Requires-Dist: einops
